cinema4d_mcp/__init__.py
cinema4d_mcp/config.py
cinema4d_mcp/server.py
cinema4d_mcp/utils.py
mseep_cinema4d_mcp-0.1.6.dist-info/licenses/LICENSE
mseep_cinema4d_mcp-0.1.6.dist-info/METADATA
mseep_cinema4d_mcp-0.1.6.dist-info/WHEEL
mseep_cinema4d_mcp-0.1.6.dist-info/entry_points.txt
mseep_cinema4d_mcp-0.1.6.dist-info/top_level.txt
mseep_cinema4d_mcp-0.1.6.dist-info/RECORD
